{"body":{"title":"US News\u7f8e\u56fd\u7efc\u5408\u5927\u5b66\u6392\u540d","groups":[{"items":[{"content":{"body":{"address":"","title":"Harvard University"},"type":"HLUniversityPreviewWithRank","name":""},"kind":"Item","rank":"1","note":"Boston, MA","score":"","chineseName":"\u54c8\u4f5b\u5927\u5b66","icon":{"body":{"address":"https://d17l1xohxe6z0o.cloudfront.net/a2/institute/harvard/logo.png","title":""},"type":"HLImage","name":""}},{"content":{"body":{"address":"","title":"Stanford University"},"type":"HLUniversityPreviewWithRank","name":""},"kind":"Item","rank":"1","note":"Stanford, CA","score":"","chineseName":"\u5c0f\u5229\u5170\u00b7\u65af\u5766\u798f\u5927\u5b66","icon":{"body":{"address":"https://d17l1xohxe6z0o.cloudfront.net/a2/institute/stanford/logo.png","title":""},"type":"HLImage","name":""}},{"content":{"body":{"address":"","title":"University of Pennsylvania (Wharton)"},"type":"HLUniversityPreviewWithRank","name":""},"kind":"Item","rank":"1","note":"Philadelphia, PA","score":"","chineseName":null,"icon":{"body":{"address":null,"title":""},"type":"HLImage","name":""}},{"content":{"body":{"address":"","title":"University of Chicago (Booth)"},"type":"HLUniversityPreviewWithRank","name":""},"kind":"Item","rank":"4","note":"Chicago, IL","score":"","chineseName":null,"icon":{"body":{"address":null,"title":""},"type":"HLImage","name":""}},{"content":{"body":{"address":"","title":"Massachusetts Institute of Technology (Sloan)"},"type":"HLUniversityPreviewWithRank","name":""},"kind":"Item","rank":"5","note":"Cambridge, MA","score":"","chineseName":null,"icon":{"body":{"address":null,"title":""},"type":"HLImage","name":""}},{"content":{"body":{"address":"","title":"Northwestern University (Kellogg)"},"type":"HLUniversityPreviewWithRank","name":""},"kind":"Item","rank":"6","note":"Evanston, IL","score":"","chineseName":null,"icon":{"body":{"address":null,"title":""},"type":"HLImage","name":""}},{"content":{"body":{"address":"","title":"University of California\u2013\u200bBerkeley (Haas)"},"type":"HLUniversityPreviewWithRank","name":""},"kind":"Item","rank":"7","note":"Berkeley, CA","score":"","chineseName":null,"icon":{"body":{"address":null,"title":""},"type":"HLImage","name":""}},{"content":{"body":{"address":"","title":"Columbia University"},"type":"HLUniversityPreviewWithRank","name":""},"kind":"Item","rank":"8","note":"New York, NY","score":"","chineseName":"\u54e5\u4f26\u6bd4\u4e9a\u5927\u5b66","icon":{"body":{"address":"https://d17l1xohxe6z0o.cloudfront.net/a2/institute/columbia/logo.png","title":""},"type":"HLImage","name":""}},{"content":{"body":{"address":"","title":"Dartmouth College (Tuck)"},"type":"HLUniversityPreviewWithRank","name":""},"kind":"Item","rank":"9","note":"Hanover, NH","score":"","chineseName":null,"icon":{"body":{"address":null,"title":""},"type":"HLImage","name":""}},{"content":{"body":{"address":"","title":"New York University (Stern)"},"type":"HLUniversityPreviewWithRank","name":""},"kind":"Item","rank":"10","note":"New York, NY","score":"","chineseName":null,"icon":{"body":{"address":null,"title":""},"type":"HLImage","name":""}},{"content":{"body":{"address":"","title":"University of Michigan\u2013\u200bAnn Arbor (Ross)"},"type":"HLUniversityPreviewWithRank","name":""},"kind":"Item","rank":"11","note":"Ann Arbor, MI","score":"","chineseName":null,"icon":{"body":{"address":null,"title":""},"type":"HLImage","name":""}},{"content":{"body":{"address":"","title":"University of Virginia (Darden)"},"type":"HLUniversityPreviewWithRank","name":""},"kind":"Item","rank":"11","note":"Charlottesville, VA","score":"","chineseName":null,"icon":{"body":{"address":null,"title":""},"type":"HLImage","name":""}},{"content":{"body":{"address":"","title":"Yale University"},"type":"HLUniversityPreviewWithRank","name":""},"kind":"Item","rank":"13","note":"New Haven, CT","score":"","chineseName":"\u8036\u9c81\u5927\u5b66","icon":{"body":{"address":"https://d17l1xohxe6z0o.cloudfront.net/a2/institute/yale/logo.png","title":""},"type":"HLImage","name":""}},{"content":{"body":{"address":"","title":"Duke University (Fuqua)"},"type":"HLUniversityPreviewWithRank","name":""},"kind":"Item","rank":"14","note":"Durham, NC","score":"","chineseName":null,"icon":{"body":{"address":null,"title":""},"type":"HLImage","name":""}},{"content":{"body":{"address":"","title":"University of Texas\u2013\u200bAustin (McCombs)"},"type":"HLUniversityPreviewWithRank","name":""},"kind":"Item","rank":"15","note":"Austin, TX","score":"","chineseName":null,"icon":{"body":{"address":null,"title":""},"type":"HLImage","name":""}},{"content":{"body":{"address":"","title":"University of California\u2013\u200bLos Angeles (Anderson)"},"type":"HLUniversityPreviewWithRank","name":""},"kind":"Item","rank":"16","note":"Los Angeles, CA","score":"","chineseName":null,"icon":{"body":{"address":null,"title":""},"type":"HLImage","name":""}},{"content":{"body":{"address":"","title":"Cornell University (Johnson)"},"type":"HLUniversityPreviewWithRank","name":""},"kind":"Item","rank":"17","note":"Ithaca, NY","score":"","chineseName":null,"icon":{"body":{"address":null,"title":""},"type":"HLImage","name":""}},{"content":{"body":{"address":"","title":"Carnegie Mellon University (Tepper)"},"type":"HLUniversityPreviewWithRank","name":""},"kind":"Item","rank":"18","note":"Pittsburgh, PA","score":"","chineseName":null,"icon":{"body":{"address":null,"title":""},"type":"HLImage","name":""}},{"content":{"body":{"address":"","title":"University of North Carolina\u2013\u200bChapel Hill (Kenan\u2013\u200b Flagler)"},"type":"HLUniversityPreviewWithRank","name":""},"kind":"Item","rank":"19","note":"Chapel Hill, NC","score":"","chineseName":null,"icon":{"body":{"address":null,"title":""},"type":"HLImage","name":""}},{"content":{"body":{"address":"","title":"Emory University (Goizueta)"},"type":"HLUniversityPreviewWithRank","name":""},"kind":"Item","rank":"20","note":"Atlanta, GA","score":"","chineseName":null,"icon":{"body":{"address":null,"title":""},"type":"HLImage","name":""}},{"content":{"body":{"address":"","title":"Indiana University\u2013\u200bBloomington (Kelley)"},"type":"HLUniversityPreviewWithRank","name":""},"kind":"Item","rank":"21","note":"Bloomington, IN","score":"","chineseName":null,"icon":{"body":{"address":null,"title":""},"type":"HLImage","name":""}},{"content":{"body":{"address":"","title":"Washington University in St. Louis (Olin)"},"type":"HLUniversityPreviewWithRank","name":""},"kind":"Item","rank":"22","note":"St. Louis, MO","score":"","chineseName":null,"icon":{"body":{"address":null,"title":""},"type":"HLImage","name":""}},{"content":{"body":{"address":"","title":"Georgetown University (McDonough)"},"type":"HLUniversityPreviewWithRank","name":""},"kind":"Item","rank":"23","note":"Washington, DC","score":"","chineseName":null,"icon":{"body":{"address":null,"title":""},"type":"HLImage","name":""}},{"content":{"body":{"address":"","title":"University of Notre Dame (Mendoza)"},"type":"HLUniversityPreviewWithRank","name":""},"kind":"Item","rank":"23","note":"Notre Dame, IN","score":"","chineseName":null,"icon":{"body":{"address":null,"title":""},"type":"HLImage","name":""}},{"content":{"body":{"address":"","title":"University of Washington (Foster)"},"type":"HLUniversityPreviewWithRank","name":""},"kind":"Item","rank":"25","note":"Seattle, WA","score":"","chineseName":null,"icon":{"body":{"address":null,"title":""},"type":"HLImage","name":""}},{"content":{"body":{"address":"","title":"Vanderbilt University (Owen)"},"type":"HLUniversityPreviewWithRank","name":""},"kind":"Item","rank":"25","note":"Nashville, TN","score":"","chineseName":null,"icon":{"body":{"address":null,"title":""},"type":"HLImage","name":""}},{"content":{"body":{"address":"","title":"Arizona State University (Carey)"},"type":"HLUniversityPreviewWithRank","name":""},"kind":"Item","rank":"27","note":"Tempe, AZ","score":"","chineseName":null,"icon":{"body":{"address":null,"title":""},"type":"HLImage","name":""}},{"content":{"body":{"address":"","title":"Brigham Young University (Marriott)"},"type":"HLUniversityPreviewWithRank","name":""},"kind":"Item","rank":"27","note":"Provo, UT","score":"","chineseName":null,"icon":{"body":{"address":null,"title":""},"type":"HLImage","name":""}},{"content":{"body":{"address":"","title":"Georgia Institute of Technology (Scheller)"},"type":"HLUniversityPreviewWithRank","name":""},"kind":"Item","rank":"27","note":"Atlanta, GA","score":"","chineseName":null,"icon":{"body":{"address":null,"title":""},"type":"HLImage","name":""}},{"content":{"body":{"address":"","title":"Ohio State University (Fisher)"},"type":"HLUniversityPreviewWithRank","name":""},"kind":"Item","rank":"27","note":"Columbus, OH","score":"","chineseName":null,"icon":{"body":{"address":null,"title":""},"type":"HLImage","name":""}},{"content":{"body":{"address":"","title":"University of Southern California (Marshall)"},"type":"HLUniversityPreviewWithRank","name":""},"kind":"Item","rank":"27","note":"Los Angeles, CA","score":"","chineseName":null,"icon":{"body":{"address":null,"title":""},"type":"HLImage","name":""}},{"content":{"body":{"address":"","title":"University of Wisconsin\u2013\u200bMadison"},"type":"HLUniversityPreviewWithRank","name":""},"kind":"Item","rank":"27","note":"Madison, WI","score":"","chineseName":"\u5a01\u65af\u5eb7\u8f9b\u5927\u5b66\u9ea6\u8fea\u900a\u5206\u6821","icon":{"body":{"address":"https://d17l1xohxe6z0o.cloudfront.net/a2/institute/wisc/logo.png","title":""},"type":"HLImage","name":""}},{"content":{"body":{"address":"","title":"Rice University (Jones)"},"type":"HLUniversityPreviewWithRank","name":""},"kind":"Item","rank":"33","note":"Houston, TX","score":"","chineseName":null,"icon":{"body":{"address":null,"title":""},"type":"HLImage","name":""}},{"content":{"body":{"address":"","title":"University of Minnesota\u2013\u200bTwin Cities (Carlson)"},"type":"HLUniversityPreviewWithRank","name":""},"kind":"Item","rank":"33","note":"Minneapolis, MN","score":"","chineseName":null,"icon":{"body":{"address":null,"title":""},"type":"HLImage","name":""}},{"content":{"body":{"address":"","title":"Michigan State University (Broad)"},"type":"HLUniversityPreviewWithRank","name":""},"kind":"Item","rank":"35","note":"East Lansing, MI","score":"","chineseName":null,"icon":{"body":{"address":null,"title":""},"type":"HLImage","name":""}},{"content":{"body":{"address":"","title":"University of Illinois\u2013\u200bUrbana\u2013\u200b Champaign"},"type":"HLUniversityPreviewWithRank","name":""},"kind":"Item","rank":"35","note":"Champaign, IL","score":"","chineseName":null,"icon":{"body":{"address":null,"title":""},"type":"HLImage","name":""}},{"content":{"body":{"address":"","title":"Texas A&M University\u2013\u200bCollege Station (Mays)"},"type":"HLUniversityPreviewWithRank","name":""},"kind":"Item","rank":"37","note":"College Station, TX","score":"","chineseName":null,"icon":{"body":{"address":null,"title":""},"type":"HLImage","name":""}},{"content":{"body":{"address":"","title":"University of Rochester (Simon)"},"type":"HLUniversityPreviewWithRank","name":""},"kind":"Item","rank":"37","note":"Rochester, NY","score":"","chineseName":null,"icon":{"body":{"address":null,"title":""},"type":"HLImage","name":""}},{"content":{"body":{"address":"","title":"University of Texas\u2013\u200bDallas"},"type":"HLUniversityPreviewWithRank","name":""},"kind":"Item","rank":"37","note":"Richardson, TX","score":"","chineseName":"\u5fb7\u514b\u8428\u65af\u5dde\u5927\u5b66\u8fbe\u62c9\u65af\u5206\u6821","icon":{"body":{"address":"https://d17l1xohxe6z0o.cloudfront.net/a2/institute/utdallas/logo.png","title":""},"type":"HLImage","name":""}},{"content":{"body":{"address":"","title":"Purdue University\u2013\u200bWest Lafayette (Krannert)"},"type":"HLUniversityPreviewWithRank","name":""},"kind":"Item","rank":"40","note":"West Lafayette, IN","score":"","chineseName":null,"icon":{"body":{"address":null,"title":""},"type":"HLImage","name":""}},{"content":{"body":{"address":"","title":"Pennsylvania State University\u2013\u200bUniversity Park (Smeal)"},"type":"HLUniversityPreviewWithRank","name":""},"kind":"Item","rank":"41","note":"University Park, PA","score":"","chineseName":null,"icon":{"body":{"address":null,"title":""},"type":"HLImage","name":""}},{"content":{"body":{"address":"","title":"University of California\u2013\u200bDavis"},"type":"HLUniversityPreviewWithRank","name":""},"kind":"Item","rank":"41","note":"Davis, CA","score":"","chineseName":"\u6234\u7ef4\u65af\u52a0\u5229\u798f\u5c3c\u4e9a\u5927\u5b66","icon":{"body":{"address":"https://d17l1xohxe6z0o.cloudfront.net/a2/institute/ucdavis/logo.png","title":""},"type":"HLImage","name":""}},{"content":{"body":{"address":"","title":"University of Florida (Hough)"},"type":"HLUniversityPreviewWithRank","name":""},"kind":"Item","rank":"41","note":"Gainesville, FL","score":"","chineseName":null,"icon":{"body":{"address":null,"title":""},"type":"HLImage","name":""}},{"content":{"body":{"address":"","title":"University of Maryland\u2013\u200bCollege Park (Smith)"},"type":"HLUniversityPreviewWithRank","name":""},"kind":"Item","rank":"41","note":"College Park, MD","score":"","chineseName":null,"icon":{"body":{"address":null,"title":""},"type":"HLImage","name":""}},{"content":{"body":{"address":"","title":"Boston College (Carroll)"},"type":"HLUniversityPreviewWithRank","name":""},"kind":"Item","rank":"45","note":"Chestnut Hill, MA","score":"","chineseName":null,"icon":{"body":{"address":null,"title":""},"type":"HLImage","name":""}},{"content":{"body":{"address":"","title":"Boston University"},"type":"HLUniversityPreviewWithRank","name":""},"kind":"Item","rank":"45","note":"Boston, MA","score":"","chineseName":"\u6ce2\u58eb\u987f\u5927\u5b66","icon":{"body":{"address":"https://d17l1xohxe6z0o.cloudfront.net/a2/institute/bu/logo.png","title":""},"type":"HLImage","name":""}},{"content":{"body":{"address":"","title":"University of California\u2013\u200bIrvine (Merage)"},"type":"HLUniversityPreviewWithRank","name":""},"kind":"Item","rank":"45","note":"Irvine, CA","score":"","chineseName":null,"icon":{"body":{"address":null,"title":""},"type":"HLImage","name":""}},{"content":{"body":{"address":"","title":"Temple University (Fox)"},"type":"HLUniversityPreviewWithRank","name":""},"kind":"Item","rank":"48","note":"Philadelphia, PA","score":"","chineseName":null,"icon":{"body":{"address":null,"title":""},"type":"HLImage","name":""}},{"content":{"body":{"address":"","title":"University of Arizona (Eller)"},"type":"HLUniversityPreviewWithRank","name":""},"kind":"Item","rank":"48","note":"Tucson, AZ","score":"","chineseName":null,"icon":{"body":{"address":null,"title":""},"type":"HLImage","name":""}},{"content":{"body":{"address":"","title":"University of Georgia (Terry)"},"type":"HLUniversityPreviewWithRank","name":""},"kind":"Item","rank":"48","note":"Athens, GA","score":"","chineseName":null,"icon":{"body":{"address":null,"title":""},"type":"HLImage","name":""}},{"content":{"body":{"address":"","title":"University of Iowa (Tippie)"},"type":"HLUniversityPreviewWithRank","name":""},"kind":"Item","rank":"51","note":"Iowa City, IA","score":"","chineseName":null,"icon":{"body":{"address":null,"title":""},"type":"HLImage","name":""}},{"content":{"body":{"address":"","title":"Northeastern University"},"type":"HLUniversityPreviewWithRank","name":""},"kind":"Item","rank":"52","note":"Boston, MA","score":"","chineseName":null,"icon":{"body":{"address":"https://d17l1xohxe6z0o.cloudfront.net/a2/institute/northeastern/logo.png","title":""},"type":"HLImage","name":""}},{"content":{"body":{"address":"","title":"University of Connecticut"},"type":"HLUniversityPreviewWithRank","name":""},"kind":"Item","rank":"52","note":"Storrs, CT","score":"","chineseName":"\u5eb7\u6d85\u72c4\u683c\u5927\u5b66","icon":{"body":{"address":"https://d17l1xohxe6z0o.cloudfront.net/a2/institute/uconn/logo.png","title":""},"type":"HLImage","name":""}},{"content":{"body":{"address":"","title":"University of Pittsburgh (Katz)"},"type":"HLUniversityPreviewWithRank","name":""},"kind":"Item","rank":"52","note":"Pittsburgh, PA","score":"","chineseName":null,"icon":{"body":{"address":null,"title":""},"type":"HLImage","name":""}},{"content":{"body":{"address":"","title":"Southern Methodist University (Cox)"},"type":"HLUniversityPreviewWithRank","name":""},"kind":"Item","rank":"55","note":"Dallas, TX","score":"","chineseName":null,"icon":{"body":{"address":null,"title":""},"type":"HLImage","name":""}},{"content":{"body":{"address":"","title":"University of Arkansas\u2013\u200bFayetteville (Walton)"},"type":"HLUniversityPreviewWithRank","name":""},"kind":"Item","rank":"55","note":"Fayetteville, AR","score":"","chineseName":null,"icon":{"body":{"address":null,"title":""},"type":"HLImage","name":""}},{"content":{"body":{"address":"","title":"University of South Carolina (Moore)"},"type":"HLUniversityPreviewWithRank","name":""},"kind":"Item","rank":"55","note":"Columbia, SC","score":"","chineseName":null,"icon":{"body":{"address":null,"title":""},"type":"HLImage","name":""}},{"content":{"body":{"address":"","title":"University of Missouri (Trulaske)"},"type":"HLUniversityPreviewWithRank","name":""},"kind":"Item","rank":"58","note":"Columbia, MO","score":"","chineseName":null,"icon":{"body":{"address":null,"title":""},"type":"HLImage","name":""}},{"content":{"body":{"address":"","title":"Wake Forest University"},"type":"HLUniversityPreviewWithRank","name":""},"kind":"Item","rank":"58","note":"Winston-Salem, NC","score":"","chineseName":"\u7ef4\u514b\u5f17\u65af\u7279\u5927\u5b66","icon":{"body":{"address":"https://d17l1xohxe6z0o.cloudfront.net/a2/institute/wfu/logo.png","title":""},"type":"HLImage","name":""}},{"content":{"body":{"address":"","title":"Rutgers, the State University of New Jersey\u2013\u200bNew Brunswick and Newark"},"type":"HLUniversityPreviewWithRank","name":""},"kind":"Item","rank":"60","note":"Newark, NJ","score":"","chineseName":null,"icon":{"body":{"address":null,"title":""},"type":"HLImage","name":""}},{"content":{"body":{"address":"","title":"University of California\u2013\u200bSan Diego (Rady)"},"type":"HLUniversityPreviewWithRank","name":""},"kind":"Item","rank":"60","note":"San Diego, CA","score":"","chineseName":null,"icon":{"body":{"address":null,"title":""},"type":"HLImage","name":""}},{"content":{"body":{"address":"","title":"University of Cincinnati (Lindner)"},"type":"HLUniversityPreviewWithRank","name":""},"kind":"Item","rank":"60","note":"Cincinnati, OH","score":"","chineseName":null,"icon":{"body":{"address":null,"title":""},"type":"HLImage","name":""}},{"content":{"body":{"address":"","title":"Tulane University (Freeman)"},"type":"HLUniversityPreviewWithRank","name":""},"kind":"Item","rank":"63","note":"New Orleans, LA","score":"","chineseName":null,"icon":{"body":{"address":null,"title":""},"type":"HLImage","name":""}},{"content":{"body":{"address":"","title":"University of Utah (Eccles)"},"type":"HLUniversityPreviewWithRank","name":""},"kind":"Item","rank":"63","note":"Salt Lake City, UT","score":"","chineseName":null,"icon":{"body":{"address":null,"title":""},"type":"HLImage","name":""}},{"content":{"body":{"address":"","title":"Babson College (Olin)"},"type":"HLUniversityPreviewWithRank","name":""},"kind":"Item","rank":"65","note":"Babson Park, MA","score":"","chineseName":null,"icon":{"body":{"address":null,"title":""},"type":"HLImage","name":""}},{"content":{"body":{"address":"","title":"Baylor University (Hankamer)"},"type":"HLUniversityPreviewWithRank","name":""},"kind":"Item","rank":"65","note":"Waco, TX","score":"","chineseName":null,"icon":{"body":{"address":null,"title":""},"type":"HLImage","name":""}},{"content":{"body":{"address":"","title":"Case Western Reserve University (Weatherhead)"},"type":"HLUniversityPreviewWithRank","name":""},"kind":"Item","rank":"65","note":"Cleveland, OH","score":"","chineseName":null,"icon":{"body":{"address":null,"title":""},"type":"HLImage","name":""}},{"content":{"body":{"address":"","title":"George Washington University"},"type":"HLUniversityPreviewWithRank","name":""},"kind":"Item","rank":"65","note":"Washington, DC","score":"","chineseName":"","icon":{"body":{"address":"https://d17l1xohxe6z0o.cloudfront.net/a2/institute/gwu/logo.png","title":""},"type":"HLImage","name":""}},{"content":{"body":{"address":"","title":"Louisiana State University\u2013\u200bBaton Rouge (Ourso)"},"type":"HLUniversityPreviewWithRank","name":""},"kind":"Item","rank":"65","note":"Baton Rouge, LA","score":"","chineseName":null,"icon":{"body":{"address":null,"title":""},"type":"HLImage","name":""}},{"content":{"body":{"address":"","title":"North Carolina State University (Jenkins)"},"type":"HLUniversityPreviewWithRank","name":""},"kind":"Item","rank":"65","note":"Raleigh, NC","score":"","chineseName":null,"icon":{"body":{"address":null,"title":""},"type":"HLImage","name":""}},{"content":{"body":{"address":"","title":"University of Oklahoma (Price)"},"type":"HLUniversityPreviewWithRank","name":""},"kind":"Item","rank":"65","note":"Norman, OK","score":"","chineseName":null,"icon":{"body":{"address":null,"title":""},"type":"HLImage","name":""}},{"content":{"body":{"address":"","title":"University of Tennessee\u2013\u200bKnoxville"},"type":"HLUniversityPreviewWithRank","name":""},"kind":"Item","rank":"65","note":"Knoxville, TN","score":"","chineseName":null,"icon":{"body":{"address":null,"title":""},"type":"HLImage","name":""}},{"content":{"body":{"address":"","title":"Iowa State University"},"type":"HLUniversityPreviewWithRank","name":""},"kind":"Item","rank":"73","note":"Ames, IA","score":"","chineseName":"\u7231\u8377\u534e\u5dde\u7acb\u5927\u5b66","icon":{"body":{"address":"https://d17l1xohxe6z0o.cloudfront.net/a2/institute/iastate/logo.png","title":""},"type":"HLImage","name":""}},{"content":{"body":{"address":"","title":"University at Buffalo\u2013\u200bSUNY"},"type":"HLUniversityPreviewWithRank","name":""},"kind":"Item","rank":"74","note":"Buffalo, NY","score":"","chineseName":"\u7ebd\u7ea6\u5dde\u7acb\u5927\u5b66\u5e03\u6cd5\u7f57\u5206\u6821","icon":{"body":{"address":"https://d17l1xohxe6z0o.cloudfront.net/a2/institute/buffalo/logo.png","title":""},"type":"HLImage","name":""}},{"content":{"body":{"address":"","title":"University of Alabama (Manderson)"},"type":"HLUniversityPreviewWithRank","name":""},"kind":"Item","rank":"74","note":"Tuscaloosa, AL","score":"","chineseName":null,"icon":{"body":{"address":null,"title":""},"type":"HLImage","name":""}},{"content":{"body":{"address":"","title":"Binghamton University\u2013\u200bSUNY"},"type":"HLUniversityPreviewWithRank","name":""},"kind":"Item","rank":"76","note":"Binghamton, NY","score":"","chineseName":null,"icon":{"body":{"address":"https://d17l1xohxe6z0o.cloudfront.net/a2/institute/binghamton/logo.png","title":""},"type":"HLImage","name":""}},{"content":{"body":{"address":"","title":"Pepperdine University (Graziadio)"},"type":"HLUniversityPreviewWithRank","name":""},"kind":"Item","rank":"76","note":"Malibu, CA","score":"","chineseName":null,"icon":{"body":{"address":null,"title":""},"type":"HLImage","name":""}},{"content":{"body":{"address":"","title":"Texas Christian University (Neeley)"},"type":"HLUniversityPreviewWithRank","name":""},"kind":"Item","rank":"76","note":"Fort Worth, TX","score":"","chineseName":null,"icon":{"body":{"address":null,"title":""},"type":"HLImage","name":""}},{"content":{"body":{"address":"","title":"Syracuse University (Whitman)"},"type":"HLUniversityPreviewWithRank","name":""},"kind":"Item","rank":"79","note":"Syracuse, NY","score":"","chineseName":null,"icon":{"body":{"address":null,"title":""},"type":"HLImage","name":""}},{"content":{"body":{"address":"","title":"University of Colorado\u2013\u200bBoulder (Leeds)"},"type":"HLUniversityPreviewWithRank","name":""},"kind":"Item","rank":"80","note":"Boulder, CO","score":"","chineseName":null,"icon":{"body":{"address":null,"title":""},"type":"HLImage","name":""}},{"content":{"body":{"address":"","title":"University of Delaware (Lerner)"},"type":"HLUniversityPreviewWithRank","name":""},"kind":"Item","rank":"80","note":"Newark, DE","score":"","chineseName":null,"icon":{"body":{"address":null,"title":""},"type":"HLImage","name":""}},{"content":{"body":{"address":"","title":"College of William and Mary (Mason)"},"type":"HLUniversityPreviewWithRank","name":""},"kind":"Item","rank":"82","note":"Williamsburg, VA","score":"","chineseName":null,"icon":{"body":{"address":null,"title":""},"type":"HLImage","name":""}},{"content":{"body":{"address":"","title":"CUNY Bernard M. Baruch College (Zicklin)"},"type":"HLUniversityPreviewWithRank","name":""},"kind":"Item","rank":"82","note":"New York, NY","score":"","chineseName":null,"icon":{"body":{"address":null,"title":""},"type":"HLImage","name":""}},{"content":{"body":{"address":"","title":"University of Kansas"},"type":"HLUniversityPreviewWithRank","name":""},"kind":"Item","rank":"82","note":"Lawrence, KS","score":"","chineseName":"\u582a\u8428\u65af\u5927\u5b66","icon":{"body":{"address":"https://d17l1xohxe6z0o.cloudfront.net/a2/institute/ku/logo.png","title":""},"type":"HLImage","name":""}},{"content":{"body":{"address":"","title":"DePaul University (Kellstadt)"},"type":"HLUniversityPreviewWithRank","name":""},"kind":"Item","rank":"85","note":"Chicago, IL","score":"","chineseName":null,"icon":{"body":{"address":null,"title":""},"type":"HLImage","name":""}},{"content":{"body":{"address":"","title":"Thunderbird School of Global Management"},"type":"HLUniversityPreviewWithRank","name":""},"kind":"Item","rank":"85","note":"Glendale, AZ","score":"","chineseName":"","icon":{"body":{"address":"https://d17l1xohxe6z0o.cloudfront.net/a2/institute/thunderbird/logo.png","title":""},"type":"HLImage","name":""}},{"content":{"body":{"address":"","title":"Claremont Graduate University (Drucker)"},"type":"HLUniversityPreviewWithRank","name":""},"kind":"Item","rank":"87","note":"Claremont, CA","score":"","chineseName":null,"icon":{"body":{"address":null,"title":""},"type":"HLImage","name":""}},{"content":{"body":{"address":"","title":"Rensselaer Polytechnic Institute (Lally)"},"type":"HLUniversityPreviewWithRank","name":""},"kind":"Item","rank":"87","note":"Troy, NY","score":"","chineseName":null,"icon":{"body":{"address":null,"title":""},"type":"HLImage","name":""}},{"content":{"body":{"address":"","title":"San Diego State University"},"type":"HLUniversityPreviewWithRank","name":""},"kind":"Item","rank":"87","note":"San Diego, CA","score":"","chineseName":null,"icon":{"body":{"address":"https://d17l1xohxe6z0o.cloudfront.net/a2/institute/sdsu/logo.png","title":""},"type":"HLImage","name":""}},{"content":{"body":{"address":"","title":"Texas Tech University (Rawls)"},"type":"HLUniversityPreviewWithRank","name":""},"kind":"Item","rank":"87","note":"Lubbock, TX","score":"","chineseName":null,"icon":{"body":{"address":null,"title":""},"type":"HLImage","name":""}},{"content":{"body":{"address":"","title":"University at Albany\u2013\u200bSUNY"},"type":"HLUniversityPreviewWithRank","name":""},"kind":"Item","rank":"87","note":"Albany, NY","score":"","chineseName":null,"icon":{"body":{"address":"https://d17l1xohxe6z0o.cloudfront.net/a2/institute/albany/logo.png","title":""},"type":"HLImage","name":""}},{"content":{"body":{"address":"","title":"Fordham University"},"type":"HLUniversityPreviewWithRank","name":""},"kind":"Item","rank":"92","note":"New York, NY","score":"","chineseName":"\u798f\u5766\u83ab\u5927\u5b66","icon":{"body":{"address":"https://d17l1xohxe6z0o.cloudfront.net/a2/institute/fordham/logo.png","title":""},"type":"HLImage","name":""}},{"content":{"body":{"address":"","title":"University of Houston (Bauer)"},"type":"HLUniversityPreviewWithRank","name":""},"kind":"Item","rank":"92","note":"Houston, TX","score":"","chineseName":null,"icon":{"body":{"address":null,"title":""},"type":"HLImage","name":""}},{"content":{"body":{"address":"","title":"University of Illinois\u2013\u200bChicago (Liautaud)"},"type":"HLUniversityPreviewWithRank","name":""},"kind":"Item","rank":"92","note":"Chicago, IL","score":"","chineseName":null,"icon":{"body":{"address":null,"title":""},"type":"HLImage","name":""}},{"content":{"body":{"address":"","title":"West Virginia University"},"type":"HLUniversityPreviewWithRank","name":""},"kind":"Item","rank":"92","note":"Morgantown, WV","score":"","chineseName":null,"icon":{"body":{"address":"https://d17l1xohxe6z0o.cloudfront.net/a2/institute/wvu/logo.png","title":""},"type":"HLImage","name":""}},{"content":{"body":{"address":"","title":"Bentley University (McCallum)"},"type":"HLUniversityPreviewWithRank","name":""},"kind":"Item","rank":"96","note":"Waltham, MA","score":"","chineseName":null,"icon":{"body":{"address":null,"title":""},"type":"HLImage","name":""}},{"content":{"body":{"address":"","title":"University of Miami"},"type":"HLUniversityPreviewWithRank","name":""},"kind":"Item","rank":"96","note":"Coral Gables, FL","score":"","chineseName":null,"icon":{"body":{"address":"https://d17l1xohxe6z0o.cloudfront.net/a2/institute/miami/logo.png","title":""},"type":"HLImage","name":""}},{"content":{"body":{"address":"","title":"University of Oregon (Lundquist)"},"type":"HLUniversityPreviewWithRank","name":""},"kind":"Item","rank":"96","note":"Eugene, OR","score":"","chineseName":null,"icon":{"body":{"address":null,"title":""},"type":"HLImage","name":""}},{"content":{"body":{"address":"","title":"University of Tulsa (Collins)"},"type":"HLUniversityPreviewWithRank","name":""},"kind":"Item","rank":"96","note":"Tulsa, OK","score":"","chineseName":null,"icon":{"body":{"address":null,"title":""},"type":"HLImage","name":""}},{"content":{"body":{"address":"","title":"American University (Kogod)"},"type":"HLUniversityPreviewWithRank","name":""},"kind":"Item","rank":"100","note":"Washington, DC","score":"","chineseName":null,"icon":{"body":{"address":null,"title":""},"type":"HLImage","name":""}},{"content":{"body":{"address":"","title":"Mississippi State University"},"type":"HLUniversityPreviewWithRank","name":""},"kind":"Item","rank":"100","note":"Mississippi State, MS","score":"","chineseName":"\u5bc6\u897f\u897f\u6bd4\u5dde\u7acb\u5927\u5b66","icon":{"body":{"address":"https://d17l1xohxe6z0o.cloudfront.net/a2/institute/msstate/logo.png","title":""},"type":"HLImage","name":""}},{"content":{"body":{"address":"","title":"University of Kentucky (Gatton)"},"type":"HLUniversityPreviewWithRank","name":""},"kind":"Item","rank":"100","note":"Lexington, KY","score":"","chineseName":null,"icon":{"body":{"address":null,"title":""},"type":"HLImage","name":""}},{"content":{"body":{"address":"","title":"University of St. Thomas"},"type":"HLUniversityPreviewWithRank","name":""},"kind":"Item","rank":"100","note":"Minneapolis, MN","score":"","chineseName":null,"icon":{"body":{"address":"https://d17l1xohxe6z0o.cloudfront.net/a2/institute/stthomas/logo.png","title":""},"type":"HLImage","name":""}},{"content":{"body":{"address":"","title":"Northern Arizona University (Franke)"},"type":"HLUniversityPreviewWithRank","name":""},"kind":"Item","rank":"104","note":"Flagstaff, AZ","score":"","chineseName":null,"icon":{"body":{"address":null,"title":""},"type":"HLImage","name":""}}],"title":"-"}],"footer":"\u66f4\u591a\u9662\u6821\u6570\u636e\u6301\u7eed\u66f4\u65b0\u4e2d"},"type":"HLList","name":""}